frds/__init__.py
frds/measures/_lerner_index.py
frds/measures/_contingent_claim_analysis.py
frds/measures/_long_run_mes.py
frds/measures/__init__.py
frds/measures/_srisk.py
frds/measures/spread.py
frds/measures/lrmes.hpp
frds/measures/_distress_insurance_premium.py
frds/measures/_probability_of_informed_trading.py
frds/measures/_z_score.py
frds/measures/_systemic_expected_shortfall.py
frds/measures/_marginal_expected_shortfall.py
frds/measures/_absorption_ratio.py
frds/measures/_option_price.py
frds/measures/lob_slope.py
frds/measures/measures_ext.cpython-311-x86_64-linux-gnu.so
frds/measures/price_impact.py
frds/measures/_kyle_lambda.py
frds/measures/measures_module.cpp
frds/measures/modified_merton/fftsmooth.py
frds/measures/modified_merton/mod_merton_computation.py
frds/measures/modified_merton/merton_solution.py
frds/measures/modified_merton/mod_merton_create_lookup.py
frds/measures/modified_merton/__init__.py
frds/measures/modified_merton/find_face_value_indiv.py
frds/measures/modified_merton/mod_single_cohort_solution.py
frds/measures/modified_merton/loan_payoff.py
frds/measures/modified_merton/mod_merton_simulation.py
frds/measures/modified_merton/mod_single_merton_create_lookup.py
frds/measures/modified_merton/mod_single_cohort_computation.py
frds/algorithms/__init__.py
frds/algorithms/_mgarch.py
frds/algorithms/_garch.py
frds/algorithms/utils/utils_module.cpp
frds/algorithms/utils/__init__.py
frds/algorithms/utils/utils_ext.cpython-311-x86_64-linux-gnu.so
frds/algorithms/utils/mgarch.hpp
frds/algorithms/utils/garch.hpp
frds/algorithms/isolation_forest/iforest_module.cpp
frds/algorithms/isolation_forest/IsolationForest.cpp
frds/algorithms/isolation_forest/IsolationForest.hpp
frds/algorithms/isolation_forest/__init__.py
frds/algorithms/isolation_forest/iforest_ext.cpython-311-x86_64-linux-gnu.so
frds/datasets/__init__.py
frds/datasets/stocks_us.csv.zip
frds/datasets/_stocks.py
frds-2.4.1.dist-info/WHEEL
frds-2.4.1.dist-info/top_level.txt
frds-2.4.1.dist-info/LICENSE
frds-2.4.1.dist-info/RECORD
frds-2.4.1.dist-info/METADATA
